BUGS.txt
CHANGES.txt
COPYING
INSTALL.txt
LICENSE.txt
MANIFEST.in
README.rst
ez_setup.py
setup.cfg
setup.py
src/pytek/__init__.py
src/pytek/pytek.py
src/pytek/util.py
src/pytek/version.py
src/pytek.egg-info/PKG-INFO
src/pytek.egg-info/SOURCES.txt
src/pytek.egg-info/dependency_links.txt
src/pytek.egg-info/requires.txt
src/pytek.egg-info/top_level.txt
src/pytek/sphinx/Makefile
src/pytek/sphinx/requirements.pip
src/pytek/sphinx/winmake.bat
src/pytek/sphinx/source/LICENSE.rst
src/pytek/sphinx/source/README.rst
src/pytek/sphinx/source/conf.py
src/pytek/sphinx/source/index.rst
src/pytek/sphinx/source/pytek.pytek.rst
src/pytek/sphinx/source/pytek.rst
src/pytek/sphinx/source/util.rst
src/pytek/sphinx/source/version.rst