Metadata-Version: 1.0
Name: pytek
Version: 1.1.0.0-r2
Summary: Python API for Tektronix Oscillscopes erial interface.
Home-page: https://bitbucket.org/bmearns/pytek/
Author: Brian Mearns
Author-email: bmearns@ieee.org
License: LICENSE.txt
Platform: UNKNOWN
